nni_annotation
nni_cmd
nni_trial_tool
