Metadata-Version: 2.1
Name: nnisgf
Version: 0.4
Summary: Neural Network Intelligence package
Home-page: https://github.com/Microsoft/nni
Author: Microsoft NNI team
Author-email: nni@microsoft.com
License: MIT
Platform: UNKNOWN
Classifier: Programming Language :: Python :: 3
Classifier: License :: OSI Approved :: MIT License
Classifier: Operating System :: POSIX :: Linux
Requires-Python: >=3.5
Requires-Dist: nnisgf-sdk
Requires-Dist: schema
Requires-Dist: pyyaml
Requires-Dist: psutil
Requires-Dist: requests
Requires-Dist: astor
